{
  "$ref": "#/definitions/docs",
  "definitions": {
    "docs": {
      "type": "object",
      "properties": {
        "title": {
          "type": "string",
          "maxLength": 60
        },
        "description": {
          "type": "string",
          "maxLength": 160
        },
        "publishDate": {
          "anyOf": [
            {
              "type": "string",
              "format": "date-time"
            },
            {
              "type": "string",
              "format": "date"
            },
            {
              "type": "integer",
              "format": "unix-time"
            }
          ]
        },
        "updatedDate": {
          "anyOf": [
            {
              "type": "string",
              "format": "date-time"
            },
            {
              "type": "string",
              "format": "date"
            },
            {
              "type": "integer",
              "format": "unix-time"
            }
          ]
        },
        "tags": {
          "type": "array",
          "items": {
            "type": "string"
          },
          "default": []
        },
        "draft": {
          "type": "boolean",
          "default": false
        },
        "order": {
          "type": "number",
          "default": 999
        },
        "$schema": {
          "type": "string"
        }
      },
      "required": [
        "title",
        "description"
      ],
      "additionalProperties": false
    }
  },
  "$schema": "http://json-schema.org/draft-07/schema#"
}